visionllm/__init__.py
visionllm/cli.py
visionllm/models/__init__.py
visionllm/models/text_to_image.py
visionllm/models/text_to_video.py
visionllm/utils/__init__.py
visionllm/utils/image_utils.py
visionllm/utils/video_utils.py
visionllm/vision_manager.py
visionllm-0.1.1.dist-info/LICENSE
visionllm-0.1.1.dist-info/METADATA
visionllm-0.1.1.dist-info/WHEEL
visionllm-0.1.1.dist-info/entry_points.txt
visionllm-0.1.1.dist-info/RECORD
