Metadata-Version: 2.3
Name: visionllm
Version: 0.1.1
Summary: A modular Python library for vision-based interactions with AI systems
License: MIT
Author: Laurent-Philippe Albou
Author-email: 24249870+lpalbou@users.noreply.github.com
Requires-Python: >=3.8
Classifier: Development Status :: 3 - Alpha
Classifier: Intended Audience :: Developers
Classifier: License :: OSI Approved :: MIT License
Classifier: Operating System :: MacOS
Classifier: Programming Language :: Python :: 3
Classifier: Programming Language :: Python :: 3.8
Classifier: Programming Language :: Python :: 3.9
Classifier: Programming Language :: Python :: 3.10
Classifier: Programming Language :: Python :: 3.11
Classifier: Programming Language :: Python :: 3.12
Classifier: Programming Language :: Python :: 3.13
Requires-Dist: numpy (>=1.20.0)
Requires-Dist: pillow (>=9.0.0)
Project-URL: Repository, https://github.com/lpalbou/visionllm
